neurocrypt_nexus-0.1.3.dist-info/METADATA
neurocrypt_nexus-0.1.3.dist-info/WHEEL
neurocrypt_nexus/__init__.py
neurocrypt_nexus/_core.cpython-311-x86_64-linux-gnu.so
neurocrypt_nexus-0.1.3.dist-info/RECORD
