Metadata-Version: 2.4
Name: neurocrypt-nexus
Version: 0.1.3
Classifier: Programming Language :: Rust
Classifier: Programming Language :: Python :: 3
Classifier: License :: OSI Approved :: MIT License
Classifier: License :: OSI Approved :: Apache Software License
Requires-Dist: maturin ; extra == 'dev'
Requires-Dist: pytest ; extra == 'dev'
Requires-Dist: ruff ; extra == 'dev'
Provides-Extra: dev
Summary: A foundational Rust/Python project.
License: MIT OR Apache-2.0
Requires-Python: >=3.8
Project-URL: Homepage, https://github.com/UTSAVS26/NeuroCrypt-Nexus
Project-URL: Bug Tracker, https://github.com/UTSAVS26/NeuroCrypt-Nexus/issues
